[
    {
        "label":"Wild Turkey",
        "image":"./data/North America/Wild Turkey.jpg",
        "link":"Wild_Turkey",
        "kingdom":"Birds",
        "continent":"North America"
    },
    {
        "label":"Grizzly bear",
        "image":"./data/North America/Grizzly bear.jpg",
        "link":"Grizzly_bear",
        "kingdom":"Animals",
        "continent":"North America"
    },
    {
        "label":"Muskox",
        "image":"./data/North America/Muskox.jpg",
        "link":"Muskox",
        "kingdom":"Animals",
        "continent":"North America"
    },
    {
        "label":"Coyote",
        "image":"./data/North America/Coyote.jpg",
        "link":"Coyote",
        "kingdom":"Animals",
        "continent":"North America"
    },
    {
        "label":"Polar bear",
        "image":"./data/North America/Polar bear.jpg",
        "link":"Polar_bear",
        "kingdom":"Animals",
        "continent":"North America"
    },
    {
        "label":"Atta (genus)",
        "image":"./data/North America/Atta (genus).jpg",
        "link":"Atta_(genus)",
        "kingdom":"Insects",
        "continent":"North America"
    },
    {
        "label":"Agkistrodon contortrix",
        "image":"./data/North America/Agkistrodon contortrix.jpg",
        "link":"Agkistrodon_contortrix",
        "kingdom":"Snakes",
        "continent":"North America"
    },
    {
        "label":"Hummingbird",
        "image":"./data/South America/Hummingbird.jpg",
        "link":"Hummingbird",
        "kingdom":"Birds",
        "continent":"South America"
    },
    {
        "label":"King Vulture",
        "image":"./data/South America/King Vulture.jpg",
        "link":"King_Vulture",
        "kingdom":"Birds",
        "continent":"South America"
    },
    {
        "label":"Andean Condor",
        "image":"./data/South America/Andean Condor.jpg",
        "link":"Andean_Condor",
        "kingdom":"Birds",
        "continent":"South America"
    },
    {
        "label":"Scarlet Macaw",
        "image":"./data/South America/Scarlet Macaw.jpg",
        "link":"Scarlet_Macaw",
        "kingdom":"Birds",
        "continent":"South America"
    },
    {
        "label":"Jaguar",
        "image":"./data/South America/Jaguar.jpg",
        "link":"Jaguar",
        "kingdom":"Animals",
        "continent":"South America"
    },
    {
        "label":"Cougar",
        "image":"./data/South America/Cougar.jpg",
        "link":"Cougar",
        "kingdom":"Animals",
        "continent":"South America"
    },
    {
        "label":"Capybara",
        "image":"./data/South America/Capybara.jpg",
        "link":"Capybara",
        "kingdom":"Animals",
        "continent":"South America"
    },
    {
        "label":"Linnaeus's two-toed sloth",
        "image":"./data/South America/Linnaeus's two-toed sloth.jpg",
        "link":"Linnaeus's_two-toed_sloth",
        "kingdom":"Animals",
        "continent":"South America"
    },
    {
        "label":"Elephant beetle",
        "image":"./data/South America/Elephant beetle.jpg",
        "link":"Elephant_beetle",
        "kingdom":"Insects",
        "continent":"South America"
    },
    {
        "label":"Lonomia",
        "image":"./data/South America/Lonomia.jpg",
        "link":"Lonomia",
        "kingdom":"Insects",
        "continent":"South America"
    },
    {
        "label":"Ostrich",
        "image":"./data/Africa/Ostrich.jpg",
        "link":"Ostrich",
        "kingdom":"Birds",
        "continent":"Africa"
    },
    {
        "label":"African Grey Parrot",
        "image":"./data/Africa/African Grey Parrot.jpg",
        "link":"African_Grey_Parrot",
        "kingdom":"Birds",
        "continent":"Africa"
    },
    {
        "label":"Leptoptilos",
        "image":"./data/Africa/Leptoptilos.jpg",
        "link":"Leptoptilos",
        "kingdom":"Birds",
        "continent":"Africa"
    },
    {
        "label":"Secretarybird",
        "image":"./data/Africa/Secretarybird.jpg",
        "link":"Secretarybird",
        "kingdom":"Birds",
        "continent":"Africa"
    },
    {
        "label":"Black Crowned Crane",
        "image":"./data/Africa/Black Crowned Crane.jpg",
        "link":"Black_Crowned_Crane",
        "kingdom":"Birds",
        "continent":"Africa"
    },
    {
        "label":"Zebra",
        "image":"./data/Africa/Zebra.jpg",
        "link":"Zebra",
        "kingdom":"Animals",
        "continent":"Africa"
    },
    {
        "label":"Yellow baboon",
        "image":"./data/Africa/Yellow baboon.jpg",
        "link":"Yellow_baboon",
        "kingdom":"Animals",
        "continent":"Africa"
    },
    {
        "label":"Giraffe",
        "image":"./data/Africa/Giraffe.jpg",
        "link":"Giraffe",
        "kingdom":"Animals",
        "continent":"Africa"
    },
    {
        "label":"Lion",
        "image":"./data/Africa/Lion.jpg",
        "link":"Lion",
        "kingdom":"Animals",
        "continent":"Africa"
    },
    {
        "label":"Impala",
        "image":"./data/Africa/Impala.jpg",
        "link":"Impala",
        "kingdom":"Animals",
        "continent":"Africa"
    },
    {
        "label":"Meerkat",
        "image":"./data/Africa/Meerkat.jpg",
        "link":"Meerkat",
        "kingdom":"Animals",
        "continent":"Africa"
    },
    {
        "label":"Tsetse fly",
        "image":"./data/Africa/Tsetse fly.jpg",
        "link":"Tsetse_fly",
        "kingdom":"Insects",
        "continent":"Africa"
    },
    {
        "label":"Black mamba",
        "image":"./data/Africa/Black mamba.jpg",
        "link":"Black_mamba",
        "kingdom":"Snakes",
        "continent":"Africa"
    },
    {
        "label":"Emu",
        "image":"./data/Australia/Emu.jpg",
        "link":"Emu",
        "kingdom":"Birds",
        "continent":"Australia"
    },
    {
        "label":"Kookaburra",
        "image":"./data/Australia/Kookaburra.jpg",
        "link":"Kookaburra",
        "kingdom":"Birds",
        "continent":"Australia"
    },
    {
        "label":"Cockatoo",
        "image":"./data/Australia/Cockatoo.jpg",
        "link":"Cockatoo",
        "kingdom":"Birds",
        "continent":"Australia"
    },
    {
        "label":"Budgerigar",
        "image":"./data/Australia/Budgerigar.jpg",
        "link":"Budgerigar",
        "kingdom":"Birds",
        "continent":"Australia"
    },
    {
        "label":"Echidna",
        "image":"./data/Australia/Echidna.jpg",
        "link":"Echidna",
        "kingdom":"Animals",
        "continent":"Australia"
    },
    {
        "label":"Kangaroo",
        "image":"./data/Australia/Kangaroo.jpg",
        "link":"Kangaroo",
        "kingdom":"Animals",
        "continent":"Australia"
    },
    {
        "label":"Koala",
        "image":"./data/Australia/Koala.jpg",
        "link":"Koala",
        "kingdom":"Animals",
        "continent":"Australia"
    },
    {
        "label":"Tasmanian Devil",
        "image":"./data/Australia/Tasmanian Devil.jpg",
        "link":"Tasmanian_Devil",
        "kingdom":"Animals",
        "continent":"Australia"
    },
    {
        "label":"Dingo",
        "image":"./data/Australia/Dingo.jpg",
        "link":"Dingo",
        "kingdom":"Animals",
        "continent":"Australia"
    },
    {
        "label":"Taipan",
        "image":"./data/Australia/Taipan.jpg",
        "link":"Taipan",
        "kingdom":"Snakes",
        "continent":"Australia"
    },
    {
        "label":"Tiger snake",
        "image":"./data/Australia/Tiger snake.jpg",
        "link":"Tiger_snake",
        "kingdom":"Snakes",
        "continent":"Australia"
    },
    {
        "label":"wisent",
        "image":"./data/Eurasia/wisent.jpg",
        "link":"Wisent",
        "kingdom":"Animals",
        "continent":"Eurasia"
    },
    {
        "label":"Giant panda",
        "image":"./data/Eurasia/Giant panda.jpg",
        "link":"Giant_Panda",
        "kingdom":"Animals",
        "continent":"Eurasia"
    },
    {
        "label":"Tiger",
        "image":"./data/Eurasia/Tiger.jpg",
        "link":"Tiger",
        "kingdom":"Animals",
        "continent":"Eurasia"
    },
    {
        "label":"Brown Bear",
        "image":"./data/Eurasia/Brown Bear.jpg",
        "link":"Brown_Bear",
        "kingdom":"Animals",
        "continent":"Eurasia"
    },
    {
        "label":"Eurasian Lynx",
        "image":"./data/Eurasia/Eurasian Lynx.jpg",
        "link":"Eurasian_Lynx",
        "kingdom":"Animals",
        "continent":"Eurasia"
    },
    {
        "label":"Snow leopard",
        "image":"./data/Eurasia/Snow leopard.jpg",
        "link":"Snow_leopard",
        "kingdom":"Animals",
        "continent":"Eurasia"
    },
    {
        "label":"Cockchafer",
        "image":"./data/Eurasia/Cockchafer.jpg",
        "link":"Cockchafer",
        "kingdom":"Insects",
        "continent":"Eurasia"
    },
    {
        "label":"Lycosa tarantula",
        "image":"./data/Eurasia/Lycosa tarantula.jpg",
        "link":"Lycosa_tarantula",
        "kingdom":"Insects",
        "continent":"Eurasia"
    },
    {
        "label":"Latrodectus tredecimguttatus",
        "image":"./data/Eurasia/Latrodectus tredecimguttatus.jpg",
        "link":"Latrodectus_tredecimguttatus",
        "kingdom":"Insects",
        "continent":"Eurasia"
    },
    {
        "label":"Asian giant hornet",
        "image":"./data/Eurasia/Asian giant hornet.jpg",
        "link":"Asian_giant_hornet",
        "kingdom":"Insects",
        "continent":"Eurasia"
    },
    {
        "label":"Attacus atlas",
        "image":"./data/Eurasia/Attacus atlas.jpg",
        "link":"Attacus_atlas",
        "kingdom":"Insects",
        "continent":"Eurasia"
    },
    {
        "label":"King Cobra",
        "image":"./data/Eurasia/King Cobra.jpg",
        "link":"King_Cobra",
        "kingdom":"Snakes",
        "continent":"Eurasia"
    },
    {
        "label":"Emperor Penguin",
        "image":"./data/Antarctica/Emperor Penguin.jpg",
        "link":"Emperor_Penguin",
        "kingdom":"Birds",
        "continent":"Antarctica"
    },
    {
        "label":"Adelie Penguin",
        "image":"./data/Antarctica/Adelie Penguin.jpg",
        "link":"Adelie_Penguin",
        "kingdom":"Birds",
        "continent":"Antarctica"
    },
    {
        "label":"Leopard seal",
        "image":"./data/Antarctica/Leopard seal.jpg",
        "link":"Leopard_seal",
        "kingdom":"Animals",
        "continent":"Antarctica"
    }
]